MANIFEST.in
README.rst
setup.py
pastis/__init__.py
pastis/algorithms.py
pastis/config.py
pastis/fastio.py
pastis/io.py
pastis/setup.py
pastis.egg-info/PKG-INFO
pastis.egg-info/SOURCES.txt
pastis.egg-info/dependency_links.txt
pastis.egg-info/not-zip-safe
pastis.egg-info/requires.txt
pastis.egg-info/top_level.txt
pastis/build/lib.linux-x86_64-2.6/pastis/__init__.py
pastis/build/lib.linux-x86_64-2.6/pastis/algorithms.py
pastis/build/lib.linux-x86_64-2.6/pastis/config.py
pastis/build/lib.linux-x86_64-2.6/pastis/io.py
pastis/build/lib.linux-x86_64-2.6/pastis/poisson_model_power_law.py
pastis/build/lib.linux-x86_64-2.6/pastis/optimization/__init__.py
pastis/build/lib.linux-x86_64-2.6/pastis/optimization/setup.py
pastis/build/lib.linux-x86_64-2.6/pastis/optimization/solver.py
pastis/build/lib.linux-x86_64-2.6/pastis/utils/__init__.py
pastis/build/lib.linux-x86_64-2.6/pastis/utils/validation.py
pastis/build/lib.linux-x86_64-2.7/pastis/__init__.py
pastis/build/lib.linux-x86_64-2.7/pastis/algorithms.py
pastis/build/lib.linux-x86_64-2.7/pastis/config.py
pastis/build/lib.linux-x86_64-2.7/pastis/fastio.py
pastis/build/lib.linux-x86_64-2.7/pastis/io.py
pastis/build/lib.linux-x86_64-2.7/pastis/poisson_model_power_law.py
pastis/build/lib.linux-x86_64-2.7/pastis/externals/__init__.py
pastis/build/lib.linux-x86_64-2.7/pastis/externals/setup.py
pastis/build/lib.linux-x86_64-2.7/pastis/externals/test_externals_setup.py
pastis/build/lib.linux-x86_64-2.7/pastis/externals/iced/__init__.py
pastis/build/lib.linux-x86_64-2.7/pastis/externals/iced/filter.py
pastis/build/lib.linux-x86_64-2.7/pastis/externals/iced/normalization.py
pastis/build/lib.linux-x86_64-2.7/pastis/externals/iced/setup.py
pastis/build/lib.linux-x86_64-2.7/pastis/externals/iced/io/__init__.py
pastis/build/lib.linux-x86_64-2.7/pastis/externals/iced/io/setup.py
pastis/build/lib.linux-x86_64-2.7/pastis/externals/iced/utils/__init__.py
pastis/build/lib.linux-x86_64-2.7/pastis/externals/iced/utils/_genome.py
pastis/build/lib.linux-x86_64-2.7/pastis/externals/iced/utils/validation.py
pastis/build/lib.linux-x86_64-2.7/pastis/externals/io/__init__.py
