Metadata-Version: 2.1
Name: pastis
Version: 0.3.3a0
Summary: A set of algorithms for the 3D inference of the genome
Home-page: UNKNOWN
Maintainer: Nelle Varoquaux
Maintainer-email: nelle.varoquaux@ensmp.fr
License: UNKNOWN
Platform: UNKNOWN
Classifier: Intended Audience :: Science/Research
Classifier: Intended Audience :: Developers
Classifier: License :: OSI Approved
Classifier: Programming Language :: C
Classifier: Programming Language :: Python
Classifier: Topic :: Software Development
Classifier: Topic :: Scientific/Engineering
Classifier: Operating System :: Microsoft :: Windows
Classifier: Operating System :: POSIX
Classifier: Operating System :: Unix
Classifier: Operating System :: MacOS
Provides-Extra: alldeps
